<?xml version="1.0" encoding="UTF-8"?>

<mule xmlns:ee="http://www.mulesoft.org/schema/mule/ee/core" xmlns:ftp="http://www.mulesoft.org/schema/mule/ftp"
	xmlns:db="http://www.mulesoft.org/schema/mule/db"
	xmlns:http="http://www.mulesoft.org/schema/mule/http" xmlns="http://www.mulesoft.org/schema/mule/core" xmlns:doc="http://www.mulesoft.org/schema/mule/documentation" xmlns:xsi="http://www.w3.org/2001/XMLSchema-instance" xsi:schemaLocation="http://www.mulesoft.org/schema/mule/core http://www.mulesoft.org/schema/mule/core/current/mule.xsd
http://www.mulesoft.org/schema/mule/http http://www.mulesoft.org/schema/mule/http/current/mule-http.xsd
http://www.mulesoft.org/schema/mule/db http://www.mulesoft.org/schema/mule/db/current/mule-db.xsd
http://www.mulesoft.org/schema/mule/ftp http://www.mulesoft.org/schema/mule/ftp/current/mule-ftp.xsd
http://www.mulesoft.org/schema/mule/ee/core http://www.mulesoft.org/schema/mule/ee/core/current/mule-ee.xsd">
	<http:listener-config name="HTTP_Listener_config" doc:name="HTTP Listener config" doc:id="a68a49a7-0f06-45e8-ac5d-87783bbc34b2" >
		<http:listener-connection host="0.0.0.0" port="8081" />
	</http:listener-config>
	<db:config name="Database_Config" doc:name="Database Config" doc:id="60b6a26a-1907-434d-bba0-c35f28a0712a" >
		<db:my-sql-connection host="localhost" port="3306" user="root" password="Remi!@#$%^&amp;*(" database="craftshopping" />
	</db:config>
	<ftp:config name="FTP_Config" doc:name="FTP Config" doc:id="ebd4d524-56dd-48a3-bc4f-ed4caa5e32dc" >
		<ftp:connection workingDir="/htdocs/yoni/craftshoppingDbRemote/outputDB/" host="ftpupload.net" username="epiz_27954235" password="3oqSKwevsD" />
	</ftp:config>
	<flow name="database2ftp" doc:id="39af3c6a-b94f-4a5a-8297-2f4144cb32c1" >
		<http:listener doc:name="Listener" doc:id="00697703-d11b-4a86-86cc-8ed2575c5f2f" config-ref="HTTP_Listener_config" path="/jenkins2"/>
		<db:select doc:name="Select" doc:id="6012fb45-b1ef-4ec6-9908-adc4ab966919" config-ref="Database_Config">
			<db:sql ><![CDATA[SELECT * FROM craftshopping.orders;
]]></db:sql>
		</db:select>
		<ee:transform doc:name="Transform Message" doc:id="a86f2dd0-d002-4f89-83fc-a67b86437c66" >
			<ee:message >
				<ee:set-payload ><![CDATA[%dw 2.0
output application/json
---
payload]]></ee:set-payload>
			</ee:message>
		</ee:transform>
		<ftp:write doc:name="Write" doc:id="3bb66bac-4248-4901-a9f1-e4da81eba377" config-ref="FTP_Config" path="orders.json" />
		<logger level="INFO" doc:name="Logger" doc:id="aa2dc917-c705-4872-9471-da5787f1128f" message='\n\nክላውድ ላይ በደንብ ገብቷል! አንበሳ! \n#[payload]'/>
	</flow>
</mule>
